{"expressie": {"titel": {"tekst": "Weeknummer 28-27"}, "publicaties": [{"distributiekanaal": "bioscoop", "sorteerdatum": "24-06-1928", "zendgemachtigden": ["NIET VAN TOEPASSING"], "ugstatus": "Onbekend", "weeknummer": "28-27", "sorteertype": "2", "type": "film", "id": "426442"}], "aanmaakdatum": "2013-11-24T06:03:44", "collecties_online": "ccbysa", "parent_id": "12070", "niveaus": [{"taakID": "522222", "taalID": "1", "themas": ["Tranche PHN goedgekeurd"], "intentieID": "1"}], "laatst_aangepastdatum": "2014-05-08T14:50:59", "id": "425497", "verwijderd": false}, "selecties": [{"eindtijd": 2593000, "docid": "6047", "tijdsduur_annotatie": "Avail: 1'13\"", "posities": [{"datum_aangemaakt": "2008-04-11T23:30:09", "dragersoort": "Programma", "volgnummer": 1, "eindeopdrager": 2593600, "annotatie": "False", "positieid": "1549822", "dragernummer": "TDP53", "dragertype": "DIGI-BETA", "technische_gegevens": "Film: 35mm; origineel negatief bij NOB; master bij RVD\nMateriaal: Zw/w\nGeluid: stom", "dragerid": "1159281", "publid": "-1", "beginopdrager": 2519600}, {"dragersoort": "Programma", "bewaarplaats": "Digitaal Archief", "dmguid": "2009013011000930800790450740014C2607C530000006568B00000D0F001452", "datum_aangemaakt": "2009-01-30T11:02:07", "sof": "2519000", "volgnummer": 1, "eindeopdrager": 2593600, "positieid": "4011539", "dragernummer": "WEEKNUMMER282-HRE00015681", "dragertype": "media archive", "dragerid": "2593654", "publid": "-1", "beginopdrager": 2519600}, {"bewaarplaats": "Digitaal Archief", "datum_aangemaakt": "2009-01-30T10:35:32", "dragersoort": "Programma", "volgnummer": 1, "eindeopdrager": 2593600, "positieid": "4011269", "dragernummer": "WEEKNUMMER282-HRE00015681.mpg", "dragertype": "MPG1", "dragerid": "2593607", "publid": "-1", "beginopdrager": 2519600}, {"bewaarplaats": "Digitaal Archief", "datum_aangemaakt": "2009-01-30T10:35:32", "dragersoort": "Programma", "volgnummer": 1, "eindeopdrager": 2593600, "positieid": "4011270", "dragernummer": "WEEKNUMMER282-HRE00015681.mxf", "dragertype": "MXF", "dragerid": "2593608", "publid": "-1", "beginopdrager": 2519600}, {"bewaarplaats": "BenG storage 1", "datum_aangemaakt": "2011-06-27T13:51:23", "dragersoort": "Programma", "volgnummer": 1, "eindeopdrager": 2593600, "positieid": "89617872", "dragernummer": "WEEKNUMMER282-HRE00015681.mxf", "dragertype": "MXF", "dragerid": "7257822", "publid": "-1", "beginopdrager": 2519600}, {"datum_aangemaakt": "2008-04-11T23:30:09", "dragersoort": "Programma", "volgnummer": 1, "eindeopdrager": 2593000, "annotatie": "False", "positieid": "1549820", "dragernummer": "28341", "dragertype": "negatiefnr.", "technische_gegevens": "Film: 35mm; origineel negatief bij NOB; master bij RVD\nMateriaal: Zw/w\nGeluid: stom", "dragerid": "1170030", "publid": "-1", "beginopdrager": 2520000}, {"datum_aangemaakt": "2008-04-11T23:30:09", "dragersoort": "Programma", "volgnummer": 1, "eindeopdrager": 2593000, "annotatie": "False", "positieid": "1549818", "dragernummer": "28-27", "dragertype": "wknr.", "technische_gegevens": "Film: 35mm; origineel negatief bij NOB; master bij RVD\nMateriaal: Zw/w\nGeluid: stom", "dragerid": "1167988", "publid": "-1", "beginopdrager": 2520000}], "parent_id": "425497", "broncatalogus": "Polygoon Hollands Nieuws", "aanmaakdatum": "2013-11-24T06:03:45", "id": "392305", "begintijd": 2520000, "verwijderd": false, "context": [{"indicatie_stom": true, "kleur": "zw/w"}], "laatst_aangepastdatum": "2014-05-08T14:50:59", "tijdsduur": 73000, "type": "Item", "opnamen": [{"datumprecisie": "exacte dag onbekend", "begindatum": "01-11-1928"}], "niveaus": [{"geografische_namen": ["Barendrecht", "Nederland", "Ridderkerk"], "trefwoorden": [{"trefwoord": "overstromingen"}, {"trefwoord": "wateroverlast"}], "taalID": "1", "themas": ["Tranche POL goedgekeurd"], "intentieID": "1", "collectie_avails": ["Polygoon Hollands Nieuws"], "annotatie": "RVD-nummer: 099-053\nPapieren: Titellijst Centrale Commissie Filmkeuring.", "beschrijving": "Dijkdoorbraak veroorzaakt ondergelopen landerijen in de buurt\nvan Ridderkerk en Barendrecht.\nSHOTS:\n-Man en jongen kijken naar groot gat in dijk 7\";\n-pan over uitgestrekte watervlakte waarin tot halverwege\nondergelopen huizen 14\";\n-man sluit vanuit bootje luik van ondergelopen huis en vaart\nweg 12\";\n-doorgebroken spoordijk met restanten rails en rommel; op\nachtergrond spoorstation 12\";\n-man vaart weg bij ondergelopen huis met bootje vol huisraad,\noa stoelen 15\";\n-arbeiders leggen bekisting aan bij dijk 8\"+5\"."}], "titel": {"tekst": "OVERSTROMING"}}], "facets": [], "reeks": {"aanmaakdatum": "2013-11-24T04:59:35", "aantalafleveringen": 0, "parent_id": "12070", "verwijderd": false, "id": "12070", "laatst_aangepastdatum": "2013-11-24T04:59:35"}, "realisatie": {"titel": {"tekst": "Polygoon Hollands Nieuws", "bron": "Avail TITEL", "type": "Titel"}, "distributiekanaal": "bioscoop", "aanmaakdatum": "2013-11-24T04:59:35", "overige_titels": [{"tekst": "polhn#Polygoon Hollands Nieuws", "bron": "Prodic", "type": "ProdicTitel"}], "parent_id": "12068", "niveaus": [{"genres": ["journaal"], "taalID": "1", "intentieID": "1", "samenvatting": "Bioscoopjournaals waarin Nederlandse onderwerpen van een bepaalde week worden gepresenteerd.", "deelcatalogi": ["Bewegend beeld/Polygoon/Hollands nieuws"], "taakID": "28573"}, {"beschrijving": "Het Polygoon-journaal is decennialang h\u00e9t bioscoopjournaal in Nederland. In januari 1922 beginnen de eerste wekelijkse filmjournaals onder de titel 'Hollandsch nieuws'. Tot 1986 blijft het Polygoonjournaal bestaan. Daarna stopt het, omdat het bioscoopjournaal definitief is 'ingehaald' door de dagelijkse televisiejournaals. Philip Bloemendal (1918-1999) is veertig jaar lang d\u00e9 stem van Polygoon.", "genres": ["Nieuws"], "taalID": "1", "taakID": "29772", "intentieID": "2"}], "laatst_aangepastdatum": "2013-11-24T04:59:35", "id": "12070", "verwijderd": false}, "werk": {"titel": {"tekst": "Polygoon bioscoopjournaal", "type": "uniforme titel"}, "aanmaakdatum": "2013-11-24T05:02:23", "overige_titels": [{"tekst": "polhn#Polygoon bioscoopjournaal", "bron": "Prodic", "type": "ProdicTitel"}], "niveaus": [{"taalID": "1", "taakID": "28553", "intentieID": "1"}], "laatst_aangepastdatum": "2013-11-24T05:02:23", "id": "12068", "verwijderd": false}}