{"expressie": {"publicaties": [{"distributiekanaal": "niet van toepassing", "zendgemachtigden": ["NIET VAN TOEPASSING"], "ugstatus": "Onbekend", "sorteertype": "0", "type": "niet van toepassing", "id": "3470060", "tijdsduur": 257680}, {"distributiekanaal": "bioscoop", "technische_annotatie": "Materiaal: zw/w\nFilm     : 35mm\nGeluid   : CO", "sorteerdatum": "05-07-1954", "zendgemachtigden": ["NIET VAN TOEPASSING"], "ugstatus": "Onbekend", "weeknummer": "54-28", "sorteertype": "2", "type": "film", "id": "17403", "tijdsduur": 257680}], "posities": [{"datum_aangemaakt": "2008-04-11T23:30:09", "dragersoort": "Programma", "eindeopdrager": 3131840, "annotatie": "False", "positieid": "561909", "dragernummer": "TDP279", "dragertype": "DIGI-BETA", "technische_gegevens": "Materiaal: zw/w\nFilm     : 35mm\nGeluid   : CO", "dragerid": "42047", "publid": "17403", "beginopdrager": 2874120}, {"datum_aangemaakt": "2009-06-11T15:44:26", "dragersoort": "Programma", "opbergeenheid": "000661-001", "geluidstype": "com opt", "formaat": "16 mm", "positieid": "34016770", "dragernummer": "000661-001", "dragertype": "FILM", "dragerid": "2835058", "publid": "3470060", "locatie": "1", "archiefstatus": "veiligstelling materiaal"}, {"dragersoort": "Programma", "bewaarplaats": "Digitaal Archief", "dmguid": "444C4755494400735315BA1D39270030F86A82030103000BE1A8C04A09000000", "datum_aangemaakt": "2008-04-11T23:30:09", "sof": "2873840", "volgnummer": 1, "eindeopdrager": 3131840, "annotatie": "False", "positieid": "561902", "dragernummer": "WEEKNUMMER542-HRE00003D50", "dragertype": "media archive", "technische_gegevens": "Materiaal: zw/w\nFilm     : 35mm\nGeluid   : CO", "dragerannotatie": "BG_8337.mpg", "dragerid": "42218", "publid": "17403", "beginopdrager": 2874120}, {"bewaarplaats": "Digitaal Archief", "datum_aangemaakt": "2008-04-11T23:30:09", "dragersoort": "Programma", "eindeopdrager": 3131840, "annotatie": "False", "positieid": "561904", "dragernummer": "BG_8337.mpg", "dragertype": "MPG1", "technische_gegevens": "Materiaal: zw/w\nFilm     : 35mm\nGeluid   : CO", "dragerid": "42220", "publid": "17403", "beginopdrager": 2874120}, {"bewaarplaats": "Digitaal Archief", "datum_aangemaakt": "2008-04-11T23:30:09", "dragersoort": "Programma", "eindeopdrager": 3131840, "annotatie": "False", "positieid": "561901", "dragernummer": "WEEKNUMMER542-HRE00003D50.mxf", "dragertype": "MXF", "technische_gegevens": "Materiaal: zw/w\nFilm     : 35mm\nGeluid   : CO", "dragerid": "131950", "publid": "17403", "beginopdrager": 2874120}, {"bewaarplaats": "BenG storage 1", "datum_aangemaakt": "2011-05-14T17:38:43", "dragersoort": "Programma", "eindeopdrager": 3131840, "annotatie": "False", "positieid": "89347740", "dragernummer": "WEEKNUMMER542-HRE00003D50.mxf", "dragertype": "MXF", "technische_gegevens": "Materiaal: zw/w\nFilm     : 35mm\nGeluid   : CO", "dragerid": "6963712", "publid": "17403", "beginopdrager": 2874120}, {"datum_aangemaakt": "2008-04-11T23:30:09", "dragersoort": "Programma", "eindeopdrager": 3131840, "annotatie": "False", "positieid": "561906", "dragernummer": "54138", "dragertype": "negatiefnr.", "technische_gegevens": "Materiaal: zw/w\nFilm     : 35mm\nGeluid   : CO", "dragerid": "42221", "publid": "17403", "beginopdrager": 2874120}, {"bewaarplaats": "Omroep.nl", "datum_aangemaakt": "2008-04-11T23:30:09", "dragersoort": "Programma", "eindeopdrager": 3131840, "annotatie": "False", "positieid": "561905", "dragernummer": "sn086003-bb.rm", "dragertype": "REAL-BREED", "technische_gegevens": "Materiaal: zw/w\nFilm     : 35mm\nGeluid   : CO", "dragerid": "42222", "publid": "17403", "beginopdrager": 2874120}, {"bewaarplaats": "Omroep.nl", "datum_aangemaakt": "2008-04-11T23:30:09", "dragersoort": "Programma", "eindeopdrager": 3131840, "annotatie": "False", "positieid": "561908", "dragernummer": "sn086003-sb.rm", "dragertype": "REAL-SMAL", "technische_gegevens": "Materiaal: zw/w\nFilm     : 35mm\nGeluid   : CO", "dragerid": "42223", "publid": "17403", "beginopdrager": 2874120}, {"datum_aangemaakt": "2008-04-11T23:30:09", "dragersoort": "Programma", "eindeopdrager": 3131840, "annotatie": "False", "positieid": "561910", "dragernummer": "VP279", "dragertype": "VHS", "technische_gegevens": "Materiaal: zw/w\nFilm     : 35mm\nGeluid   : CO", "dragerid": "42052", "publid": "17403", "beginopdrager": 2874120}, {"bewaarplaats": "Omroep.nl", "datum_aangemaakt": "2008-04-11T23:30:09", "dragersoort": "Programma", "eindeopdrager": 3131840, "annotatie": "False", "positieid": "561907", "dragernummer": "sn086003-bb.wmv", "dragertype": "WIN-MEDIA-BREED", "technische_gegevens": "Materiaal: zw/w\nFilm     : 35mm\nGeluid   : CO", "dragerid": "42225", "publid": "17403", "beginopdrager": 2874120}, {"bewaarplaats": "Omroep.nl", "datum_aangemaakt": "2008-04-11T23:30:09", "dragersoort": "Programma", "eindeopdrager": 3131840, "annotatie": "False", "positieid": "566537", "dragernummer": "sn086003-sb.wmv", "dragertype": "WIN-MEDIA-SMAL", "technische_gegevens": "Materiaal: zw/w\nFilm     : 35mm\nGeluid   : CO", "dragerid": "42226", "publid": "17403", "beginopdrager": 2874120}, {"datum_aangemaakt": "2008-04-11T23:30:09", "dragersoort": "Programma", "eindeopdrager": 3131840, "annotatie": "False", "positieid": "561903", "dragernummer": "54-28", "dragertype": "wknr.", "technische_gegevens": "Materiaal: zw/w\nFilm     : 35mm\nGeluid   : CO", "dragerid": "42055", "publid": "17403", "beginopdrager": 2874120}, {"bewaarplaats": "OnderwijsStorage", "datum_aangemaakt": "2008-04-11T23:30:09", "dragersoort": "Programma", "eindeopdrager": 3131840, "annotatie": "False", "positieid": "1396588", "dragernummer": "BG_8337.wmv", "dragertype": "WMV", "technische_gegevens": "Materiaal: zw/w\nFilm     : 35mm\nGeluid   : CO", "dragerid": "1152323", "publid": "17403", "beginopdrager": 2874120}], "aanmaakdatum": "2013-11-24T05:11:10", "collecties_online": "ccbysa", "parent_id": "12070", "niveaus": [{"taalID": "1", "taakID": "29286", "intentieID": "1"}, {"taalID": "1", "themas": ["Medialounge / Medialounge / diversen"], "intentieID": "2", "samenvatting": "Tour de France start in Nederland.", "taakID": "29287", "beschrijving": "In 1954 gaat de wielerronde voor het eerst buiten Frankrijk van start. Het Olympisch Stadion in Amsterdam is het decor. \nDe eerste etappe van Amsterdam naar Brasschaat wordt door een Nederlandse renner gewonnen. In het Belgische grensplaatsje is Wout Wagtmans de snelste. En als toetje op deze succesvolle Nederlandse wielerdag krijgt Wagtmans ook nog de gele leiderstrui om de schouders."}], "laatst_aangepastdatum": "2014-05-08T14:56:12", "tijdsduur": 257680, "id": "17403", "verwijderd": false, "titel": {"tekst": "Weeknummer 54-28", "type": "Titel"}}, "selecties": [{"docid": "15041", "titel": {"tekst": "DE TOUR DE FRANCE 1954", "bron": "Avail TITEL", "type": "Titel"}, "posities": [{"datum_aangemaakt": "2008-04-11T23:30:09", "dragersoort": "Programma", "eindeopdrager": 3130000, "annotatie": "False", "positieid": "1200301", "dragernummer": "TDP279", "dragertype": "DIGI-BETA", "technische_gegevens": "Materiaal: zw/w\nFilm     : 35mm\nGeluid   : CO", "dragerid": "42047", "publid": "-1", "beginopdrager": 2874000}, {"sortering": "2", "datum_aangemaakt": "2009-06-11T15:44:26", "dragersoort": "Programma", "volgnummer": 2, "locatie": "1", "opbergeenheid": "000661-001", "geluidstype": "com opt", "formaat": "16 mm", "annotatie": "False", "positieid": "34016771", "dragernummer": "000661-001", "dragertype": "FILM", "technische_gegevens": "FILM 16mm zw/w opt.gel", "dragerid": "2835058", "publid": "-1", "beginopdrager": 1167000, "eindeopdrager": 1437000, "archiefstatus": "veiligstelling materiaal"}, {"dragersoort": "Programma", "bewaarplaats": "Digitaal Archief", "dmguid": "444C4755494400735315BA1D39270030F86A82030103000BE1A8C04A09000000", "sortering": "1", "datum_aangemaakt": "2008-04-11T23:30:09", "sof": "2873840", "volgnummer": 1, "eindeopdrager": 3130000, "annotatie": "False", "positieid": "1200308", "dragernummer": "WEEKNUMMER542-HRE00003D50", "dragertype": "media archive", "technische_gegevens": "Materiaal: zw/w\nFilm     : 35mm\nGeluid   : CO", "dragerannotatie": "BG_8337.mpg", "dragerid": "42218", "publid": "-1", "beginopdrager": 2874000}, {"bewaarplaats": "Digitaal Archief", "datum_aangemaakt": "2008-04-11T23:30:09", "dragersoort": "Programma", "eindeopdrager": 3130000, "annotatie": "False", "positieid": "1200306", "dragernummer": "BG_8337.mpg", "dragertype": "MPG1", "technische_gegevens": "Materiaal: zw/w\nFilm     : 35mm\nGeluid   : CO", "dragerid": "42220", "publid": "-1", "beginopdrager": 2874000}, {"bewaarplaats": "Digitaal Archief", "datum_aangemaakt": "2008-04-11T23:30:09", "dragersoort": "Programma", "eindeopdrager": 3130000, "annotatie": "False", "positieid": "1200309", "dragernummer": "WEEKNUMMER542-HRE00003D50.mxf", "dragertype": "MXF", "technische_gegevens": "Materiaal: zw/w\nFilm     : 35mm\nGeluid   : CO", "dragerid": "131950", "publid": "-1", "beginopdrager": 2874000}, {"bewaarplaats": "BenG storage 1", "datum_aangemaakt": "2011-05-14T17:38:43", "dragersoort": "Programma", "eindeopdrager": 3130000, "annotatie": "False", "positieid": "89347739", "dragernummer": "WEEKNUMMER542-HRE00003D50.mxf", "dragertype": "MXF", "technische_gegevens": "Materiaal: zw/w\nFilm     : 35mm\nGeluid   : CO", "dragerid": "6963712", "publid": "-1", "beginopdrager": 2874000}, {"datum_aangemaakt": "2008-04-11T23:30:09", "dragersoort": "Programma", "eindeopdrager": 3130000, "annotatie": "False", "positieid": "1200304", "dragernummer": "54138", "dragertype": "negatiefnr.", "technische_gegevens": "Materiaal: zw/w\nFilm     : 35mm\nGeluid   : CO", "dragerid": "42221", "publid": "-1", "beginopdrager": 2874000}, {"bewaarplaats": "Omroep.nl", "datum_aangemaakt": "2008-04-11T23:30:09", "dragersoort": "Programma", "eindeopdrager": 3130000, "annotatie": "False", "positieid": "1200305", "dragernummer": "sn086003-bb.rm", "dragertype": "REAL-BREED", "technische_gegevens": "Materiaal: zw/w\nFilm     : 35mm\nGeluid   : CO", "dragerid": "42222", "publid": "-1", "beginopdrager": 2874000}, {"bewaarplaats": "Omroep.nl", "datum_aangemaakt": "2008-04-11T23:30:09", "dragersoort": "Programma", "eindeopdrager": 3130000, "annotatie": "False", "positieid": "1200302", "dragernummer": "sn086003-sb.rm", "dragertype": "REAL-SMAL", "technische_gegevens": "Materiaal: zw/w\nFilm     : 35mm\nGeluid   : CO", "dragerid": "42223", "publid": "-1", "beginopdrager": 2874000}, {"datum_aangemaakt": "2008-04-11T23:30:09", "dragersoort": "Programma", "eindeopdrager": 3130000, "annotatie": "False", "positieid": "1200300", "dragernummer": "VP279", "dragertype": "VHS", "technische_gegevens": "Materiaal: zw/w\nFilm     : 35mm\nGeluid   : CO", "dragerid": "42052", "publid": "-1", "beginopdrager": 2874000}, {"bewaarplaats": "Omroep.nl", "datum_aangemaakt": "2008-04-11T23:30:09", "dragersoort": "Programma", "eindeopdrager": 3130000, "annotatie": "False", "positieid": "1200303", "dragernummer": "sn086003-bb.wmv", "dragertype": "WIN-MEDIA-BREED", "technische_gegevens": "Materiaal: zw/w\nFilm     : 35mm\nGeluid   : CO", "dragerid": "42225", "publid": "-1", "beginopdrager": 2874000}, {"bewaarplaats": "Omroep.nl", "datum_aangemaakt": "2008-04-11T23:30:09", "dragersoort": "Programma", "eindeopdrager": 3130000, "annotatie": "False", "positieid": "1200310", "dragernummer": "sn086003-sb.wmv", "dragertype": "WIN-MEDIA-SMAL", "technische_gegevens": "Materiaal: zw/w\nFilm     : 35mm\nGeluid   : CO", "dragerid": "42226", "publid": "-1", "beginopdrager": 2874000}, {"datum_aangemaakt": "2008-04-11T23:30:09", "dragersoort": "Programma", "eindeopdrager": 3130000, "annotatie": "False", "positieid": "1200307", "dragernummer": "54-28", "dragertype": "wknr.", "technische_gegevens": "Materiaal: zw/w\nFilm     : 35mm\nGeluid   : CO", "dragerid": "42055", "publid": "-1", "beginopdrager": 2874000}], "broncatalogus": "Polygoon Hollands Nieuws", "aanmaakdatum": "2013-11-24T05:11:11", "maker": [{"naam": "Bloemendal, Philip", "functies": ["commentaar"]}], "parent_id": "17403", "niveaus": [{"geografische_namen": ["Den Haag", "Rotterdam", "Nederland", "Noordwijk aan Zee", "Belgi\u00eb", "Brasschaat", "Scheveningen", "Haarlem", "Amsterdam", "Noord-Brabant"], "trefwoorden": [{"trefwoord": "medische keuringen"}, {"trefwoord": "wielrennen"}], "persoonsnamen": ["Wagtmans, Wout", "Roks, Thijs", "Voorting, Gerrit", "Tetzner, Hans", "Est, Wim van", "Breenen, Hein van", "Pellenaars, Kees", "Faanhof, Henk", "Goddet, Jacques", "Ailly, A.J. d'", "Nolten, Jan", "Koblet, Hugo", "Bobet, Louison"], "namen": ["Tour de France", "Olympisch Stadion"], "taalID": "1", "intentieID": "1", "collectie_avails": ["Polygoon Hollands Nieuws"], "annotatie": "Toelichting tijdsduur: Avail: 4'16\" (124 mtr.)", "beschrijving": "Voorbereiding voor de Tour de France in het Olympisch stadion te Amsterdam, met oa Jean Garnault, secretaris-generaal van de Tour en Jacques Goddet, directeur-generaal van de Tour, in hun kantoren en mecaniciens met fietsenframes. Een dag voor het begin komen Wout Wagtmans (per auto) en Louison Bobet, winnaar 1953, het stadion verkennen. De renners Jan Nolten en Gerrit Voorting worden onder het oog van dr. Tetzner medisch gecontroleerd.\nDe volgende dag staan de Zwitserse renners K\u00fcbler en Hugo Koblet klaar voor de ceremoni\u00eble start, alsmede de Nederlandse ploeg: Hein van Breenen, Nico van Est, Henk Faanhof, Jules Maenen, Thijs Roks, Wagtmans, Volten, Voorting en Van Est. Goddet staat tegen een auto geleund terwijl burgemeester D'Ailly te midden van de Belgische renners een lint doorknipt. Wim van Est gaat aan kop van de Nederlandse ploeg het stadion uit, met daar achter ploegleider Kees Pellenaars in een auto. De rit van het stadion naar de Sloterweg, de plaats van de offici\u00eble start,\nworden de renners door Amsterdammers toegejuicht. Via Haarlem en Noordwijk gaat het naar Den Haag. Voor Scheveningen weet Koblet korte tijd aan het peloton te ontsnappen. Via Rotterdam, waar de ploegleiders etenspakketten uitdelen, en Dordrecht gaan de renners naar de Moerdijkbrug. In Brabant weet Wout Wagtmans een voorsprong te nemen, waarna hij bij de grens gezelschap krijgt van 20 renners. In Brasschaat gaat Wagtmans als eerste over de finish, waarna hij wordt omhelsd door Pellenaars en de gele trui aantrekt."}], "id": "14724", "laatst_aangepastdatum": "2014-05-08T14:56:12", "type": "Item", "opnamen": [{"begindatum": "07-07-1954"}, {"begindatum": "08-07-1954"}], "verwijderd": false, "tijdsduur": 256000}], "facets": [], "reeks": {"aanmaakdatum": "2013-11-24T04:59:35", "aantalafleveringen": 0, "parent_id": "12070", "verwijderd": false, "id": "12070", "laatst_aangepastdatum": "2013-11-24T04:59:35"}, "keyframesets": [{"epguid": "ab55ae8d-fe8d-493e-b2c8-f1ae062d5f14", "dmguid": "444C4755494400735315BA1D39270030F86A82030103000BE1A8C04A09000000", "numberOfKeyframes": 241, "timecodes": [0, 120, 160, 6320, 6360, 10880, 10920, 13320, 13360, 15880, 15920, 22840, 25480, 26840, 30880, 30920, 35000, 35040, 36720, 37360, 37840, 39160, 39200, 43120, 43160, 44160, 45200, 46200, 47400, 47440, 53160, 53200, 55680, 56200, 58560, 59440, 59480, 67480, 67520, 72320, 77000, 77040, 79960, 80000, 86000, 86040, 88320, 88360, 90440, 93560, 93600, 95240, 95680, 95920, 97640, 97680, 98680, 99200, 99440, 99480, 100240, 100520, 100920, 103440, 104000, 104080, 106360, 107080, 107480, 109040, 110760, 110800, 112960, 114400, 115600, 115640, 116560, 116600, 119600, 122600, 122680, 123160, 126960, 132200, 132520, 132960, 135760, 135800, 139680, 139720, 145760, 145800, 145840, 146240, 147320, 148160, 148200, 149360, 150800, 151040, 151440, 152800, 152840, 154240, 154960, 155240, 156320, 156480, 157120, 158800, 158840, 162240, 165040, 170240, 174760, 174800, 180800, 180840, 182800, 182840, 185560, 185800, 186360, 189960, 190000, 190640, 191080, 191320, 191800, 192200, 192320, 192360, 192440, 192760, 192880, 193000, 193120, 193240, 193360, 193480, 193760, 194160, 194560, 194800, 194920, 195000, 195160, 195560, 196520, 196560, 196920, 197160, 197320, 198080, 198160, 198400, 198480, 198800, 199040, 200640, 201040, 201280, 201360, 201440, 201680, 202000, 202560, 203240, 203480, 203560, 203600, 203880, 204280, 204720, 205000, 205120, 205440, 205560, 206000, 206120, 206720, 207520, 207560, 207720, 209960, 211360, 211400, 213040, 213840, 214000, 214160, 214720, 215400, 215480, 215880, 215960, 216720, 217120, 217560, 219000, 219040, 220720, 220760, 224480, 226400, 227440, 229640, 229680, 231280, 231440, 231840, 233320, 233720, 234080, 234840, 236040, 236920, 237000, 237120, 237560, 238000, 238560, 239480, 239760, 240400, 240440, 241320, 241680, 241720, 243760, 243800, 244320, 246240, 247240, 247480, 247840, 249840, 251080, 251880, 251920, 257680]}], "realisatie": {"titel": {"tekst": "Polygoon Hollands Nieuws", "bron": "Avail TITEL", "type": "Titel"}, "distributiekanaal": "bioscoop", "aanmaakdatum": "2013-11-24T04:59:35", "overige_titels": [{"tekst": "polhn#Polygoon Hollands Nieuws", "bron": "Prodic", "type": "ProdicTitel"}], "parent_id": "12068", "niveaus": [{"genres": ["journaal"], "taalID": "1", "intentieID": "1", "samenvatting": "Bioscoopjournaals waarin Nederlandse onderwerpen van een bepaalde week worden gepresenteerd.", "deelcatalogi": ["Bewegend beeld/Polygoon/Hollands nieuws"], "taakID": "28573"}, {"beschrijving": "Het Polygoon-journaal is decennialang h\u00e9t bioscoopjournaal in Nederland. In januari 1922 beginnen de eerste wekelijkse filmjournaals onder de titel 'Hollandsch nieuws'. Tot 1986 blijft het Polygoonjournaal bestaan. Daarna stopt het, omdat het bioscoopjournaal definitief is 'ingehaald' door de dagelijkse televisiejournaals. Philip Bloemendal (1918-1999) is veertig jaar lang d\u00e9 stem van Polygoon.", "genres": ["Nieuws"], "taalID": "1", "taakID": "29772", "intentieID": "2"}], "laatst_aangepastdatum": "2013-11-24T04:59:35", "id": "12070", "verwijderd": false}, "werk": {"titel": {"tekst": "Polygoon bioscoopjournaal", "type": "uniforme titel"}, "aanmaakdatum": "2013-11-24T05:02:23", "overige_titels": [{"tekst": "polhn#Polygoon bioscoopjournaal", "bron": "Prodic", "type": "ProdicTitel"}], "niveaus": [{"taalID": "1", "taakID": "28553", "intentieID": "1"}], "laatst_aangepastdatum": "2013-11-24T05:02:23", "id": "12068", "verwijderd": false}}