{"expressie": {"publicaties": [{"distributiekanaal": "niet van toepassing", "zendgemachtigden": ["NIET VAN TOEPASSING"], "ugstatus": "Onbekend", "sorteertype": "0", "type": "niet van toepassing", "id": "3651387"}, {"distributiekanaal": "bioscoop", "sorteerdatum": "18-10-1965", "zendgemachtigden": ["NIET VAN TOEPASSING"], "ugstatus": "Onbekend", "weeknummer": "66-42", "sorteertype": "2", "type": "film", "id": "413931"}], "posities": [{"datum_aangemaakt": "2009-09-02T17:21:48", "dragersoort": "Programma", "opbergeenheid": "000801-001", "dragerannotatie": "00:00:00 = eerste beeld van eerste item op rol", "geluidstype": "com opt", "formaat": "16 mm", "annotatie": "False", "positieid": "43996759", "dragernummer": "000801-001", "dragertype": "FILM", "technische_gegevens": "FILM: 16mm zw/w opt.gel\nEngelse ondertiteling", "depotstatus": "in depot", "dragerid": "3046531", "publid": "3651387", "locatie": "6", "archiefstatus": "veiligstelling materiaal"}], "aanmaakdatum": "2013-11-24T07:09:46", "parent_id": "12070", "niveaus": [{"taakID": "509704", "taalID": "1", "themas": ["Tranche PHN goedgekeurd"], "intentieID": "1"}], "laatst_aangepastdatum": "2013-11-24T07:09:46", "id": "412990", "verwijderd": false, "titel": {"tekst": "Weeknummer 66-42"}}, "selecties": [{"eindtijd": 534000, "docid": "18336", "tijdsduur_annotatie": "Avail: 1'46\" (51 mtr.)", "posities": [{"datum_aangemaakt": "2008-04-11T23:30:09", "dragersoort": "Programma", "volgnummer": 1, "eindeopdrager": 534160, "annotatie": "False", "positieid": "1457756", "dragernummer": "TDP385", "dragertype": "DIGI-BETA", "technische_gegevens": "Materiaal: zw/w\nFilm     : 35mm\nGeluid   : CO", "dragerid": "40693", "publid": "-1", "beginopdrager": 427360}, {"datum_aangemaakt": "2009-09-02T17:21:48", "dragersoort": "Programma", "volgnummer": 2, "locatie": "6", "opbergeenheid": "000801-001", "dragerannotatie": "00:00:00 = eerste beeld van eerste item op rol", "geluidstype": "com opt", "formaat": "16 mm", "annotatie": "False", "positieid": "43996760", "dragernummer": "000801-001", "dragertype": "FILM", "technische_gegevens": "FILM: 16mm zw/w opt.gel\nEngelse ondertiteling", "depotstatus": "in depot", "dragerid": "3046531", "publid": "-1", "beginopdrager": 1080000, "eindeopdrager": 1192000, "archiefstatus": "veiligstelling materiaal"}, {"dragersoort": "Programma", "bewaarplaats": "Digitaal Archief", "dmguid": "2009020916425630800790450740014C2607C530000006568B00000D0F004672", "datum_aangemaakt": "2009-02-09T16:45:03", "sof": "427000", "volgnummer": 1, "eindeopdrager": 534160, "positieid": "4232734", "dragernummer": "WEEKNUMMER664-HRE000166EE", "dragertype": "media archive", "dragerid": "2604577", "publid": "-1", "beginopdrager": 427360}, {"bewaarplaats": "Digitaal Archief", "datum_aangemaakt": "2009-02-09T13:57:26", "dragersoort": "Programma", "volgnummer": 1, "eindeopdrager": 534160, "positieid": "4157532", "dragernummer": "WEEKNUMMER664-HRE000166EE.mpg", "dragertype": "MPG1", "dragerid": "2604332", "publid": "-1", "beginopdrager": 427360}, {"bewaarplaats": "Digitaal Archief", "datum_aangemaakt": "2009-02-09T13:57:26", "dragersoort": "Programma", "volgnummer": 1, "eindeopdrager": 534160, "positieid": "4157533", "dragernummer": "WEEKNUMMER664-HRE000166EE.mxf", "dragertype": "MXF", "dragerid": "2604333", "publid": "-1", "beginopdrager": 427360}, {"bewaarplaats": "BenG storage 1", "datum_aangemaakt": "2011-07-04T16:56:38", "dragersoort": "Programma", "volgnummer": 1, "eindeopdrager": 534160, "positieid": "89662932", "dragernummer": "WEEKNUMMER664-HRE000166EE.mxf", "dragertype": "MXF", "dragerid": "7310633", "publid": "-1", "beginopdrager": 427360}, {"datum_aangemaakt": "2008-04-11T23:30:09", "dragersoort": "Programma", "volgnummer": 1, "eindeopdrager": 534000, "annotatie": "False", "positieid": "1457754", "dragernummer": "66156", "dragertype": "negatiefnr.", "technische_gegevens": "Materiaal: zw/w\nFilm     : 35mm\nGeluid   : CO", "dragerid": "1161050", "publid": "-1", "beginopdrager": 428000}, {"datum_aangemaakt": "2008-04-11T23:30:09", "dragersoort": "Programma", "volgnummer": 1, "eindeopdrager": 534000, "annotatie": "False", "positieid": "1457758", "dragernummer": "VP385", "dragertype": "VHS", "technische_gegevens": "Materiaal: zw/w\nFilm     : 35mm\nGeluid   : CO", "dragerid": "40698", "publid": "-1", "beginopdrager": 428000}, {"datum_aangemaakt": "2008-04-11T23:30:09", "dragersoort": "Programma", "volgnummer": 1, "eindeopdrager": 534000, "annotatie": "False", "positieid": "1457752", "dragernummer": "66-42", "dragertype": "wknr.", "technische_gegevens": "Materiaal: zw/w\nFilm     : 35mm\nGeluid   : CO", "dragerid": "1158317", "publid": "-1", "beginopdrager": 428000}], "parent_id": "412990", "broncatalogus": "Polygoon Hollands Nieuws", "aanmaakdatum": "2013-11-24T07:13:14", "maker": [{"naam": "Bloemendal, Philip", "functies": ["commentaar"]}], "begintijd": 428000, "niveaus": [{"geografische_namen": ["Nederland", "Zaandam"], "trefwoorden": [{"trefwoord": "musea"}, {"trefwoord": "restaurants"}, {"trefwoord": "woningen"}], "namen": ["Zaanse Schans"], "taalID": "1", "themas": ["Tranche POL goedgekeurd"], "intentieID": "1", "collectie_avails": ["Polygoon Hollands Nieuws"], "beschrijving": "De Zaanse Schans te Zaandam, waar houten huizen uit de Zaan,\ndie moesten wijken voor de industrie, bijeen zijn gebracht in\neen openluchtmuseum. De vlaggen hangen uit voor de\ningebruikname van het restaurant De Swarte Walvis. Met verder\neen int. van een huis met tegeltableaus, bedsteden en\nversierde plafonds, het Jagershuis uit 1620 en molens."}], "context": [{"kleur": "zw/w"}], "id": "379810", "laatst_aangepastdatum": "2013-11-24T07:13:14", "tijdsduur": 106000, "type": "Item", "opnamen": [{"datumprecisie": "exacte dag onbekend", "begindatum": "01-10-1966"}], "verwijderd": false, "titel": {"tekst": "ZAANSE SCHANS"}}], "facets": [], "reeks": {"aanmaakdatum": "2013-11-24T04:59:35", "aantalafleveringen": 0, "parent_id": "12070", "verwijderd": false, "id": "12070", "laatst_aangepastdatum": "2013-11-24T04:59:35"}, "realisatie": {"titel": {"tekst": "Polygoon Hollands Nieuws", "bron": "Avail TITEL", "type": "Titel"}, "distributiekanaal": "bioscoop", "aanmaakdatum": "2013-11-24T04:59:35", "overige_titels": [{"tekst": "polhn#Polygoon Hollands Nieuws", "bron": "Prodic", "type": "ProdicTitel"}], "parent_id": "12068", "niveaus": [{"genres": ["journaal"], "taalID": "1", "intentieID": "1", "samenvatting": "Bioscoopjournaals waarin Nederlandse onderwerpen van een bepaalde week worden gepresenteerd.", "deelcatalogi": ["Bewegend beeld/Polygoon/Hollands nieuws"], "taakID": "28573"}, {"beschrijving": "Het Polygoon-journaal is decennialang h\u00e9t bioscoopjournaal in Nederland. In januari 1922 beginnen de eerste wekelijkse filmjournaals onder de titel 'Hollandsch nieuws'. Tot 1986 blijft het Polygoonjournaal bestaan. Daarna stopt het, omdat het bioscoopjournaal definitief is 'ingehaald' door de dagelijkse televisiejournaals. Philip Bloemendal (1918-1999) is veertig jaar lang d\u00e9 stem van Polygoon.", "genres": ["Nieuws"], "taalID": "1", "taakID": "29772", "intentieID": "2"}], "laatst_aangepastdatum": "2013-11-24T04:59:35", "id": "12070", "verwijderd": false}, "werk": {"titel": {"tekst": "Polygoon bioscoopjournaal", "type": "uniforme titel"}, "aanmaakdatum": "2013-11-24T05:02:23", "overige_titels": [{"tekst": "polhn#Polygoon bioscoopjournaal", "bron": "Prodic", "type": "ProdicTitel"}], "niveaus": [{"taalID": "1", "taakID": "28553", "intentieID": "1"}], "laatst_aangepastdatum": "2013-11-24T05:02:23", "id": "12068", "verwijderd": false}}