{"expressie": {"titel": {"tekst": "Weeknummer 75-43"}, "publicaties": [{"distributiekanaal": "bioscoop", "sorteerdatum": "20-10-1975", "zendgemachtigden": ["NIET VAN TOEPASSING"], "ugstatus": "Onbekend", "weeknummer": "75-43", "sorteertype": "2", "type": "film", "id": "425257"}], "aanmaakdatum": "2013-11-24T06:14:56", "collecties_online": "ccbysa", "parent_id": "12070", "niveaus": [{"taakID": "521037", "taalID": "1", "themas": ["Tranche PHN goedgekeurd"], "intentieID": "1"}], "laatst_aangepastdatum": "2014-05-08T15:02:49", "id": "424312", "verwijderd": false}, "selecties": [{"eindtijd": 2371000, "docid": "20202", "tijdsduur_annotatie": "Avail: 1'45\" (50 mtr.)", "posities": [{"datum_aangemaakt": "2008-04-11T23:30:09", "dragersoort": "Programma", "volgnummer": 1, "eindeopdrager": 2372000, "annotatie": "False", "positieid": "1541036", "dragernummer": "TDP442", "dragertype": "DIGI-BETA", "technische_gegevens": "Materiaal: zw/w\nFilm     : 35mm\nGeluid   : CO", "dragerid": "53376", "publid": "-1", "beginopdrager": 2265000}, {"dragersoort": "Programma", "bewaarplaats": "Digitaal Archief", "dmguid": "2009042011505040800790450740014C2607C530000000540B00000D0F015724", "datum_aangemaakt": "2009-04-20T11:52:20", "sof": "2265000", "volgnummer": 1, "eindeopdrager": 2372000, "positieid": "10189215", "dragernummer": "WEEKNUMMER754-HRE0001A739", "dragertype": "media archive", "dragerid": "2760493", "publid": "-1", "beginopdrager": 2265000}, {"bewaarplaats": "Digitaal Archief", "datum_aangemaakt": "2009-04-20T10:52:05", "dragersoort": "Programma", "volgnummer": 1, "eindeopdrager": 2372000, "positieid": "10186175", "dragernummer": "WEEKNUMMER754-HRE0001A739.mpg", "dragertype": "MPG1", "dragerid": "2760406", "publid": "-1", "beginopdrager": 2265000}, {"bewaarplaats": "Digitaal Archief", "datum_aangemaakt": "2009-04-20T10:52:05", "dragersoort": "Programma", "volgnummer": 1, "eindeopdrager": 2372000, "positieid": "10186176", "dragernummer": "WEEKNUMMER754-HRE0001A739.mxf", "dragertype": "MXF", "dragerid": "2760407", "publid": "-1", "beginopdrager": 2265000}, {"bewaarplaats": "BenG storage 1", "datum_aangemaakt": "2011-06-19T16:21:59", "dragersoort": "Programma", "volgnummer": 1, "eindeopdrager": 2372000, "positieid": "89555800", "dragernummer": "WEEKNUMMER754-HRE0001A739.mxf", "dragertype": "MXF", "dragerid": "7164262", "publid": "-1", "beginopdrager": 2265000}, {"datum_aangemaakt": "2008-04-11T23:30:09", "dragersoort": "Programma", "volgnummer": 1, "eindeopdrager": 2371000, "annotatie": "False", "positieid": "1541034", "dragernummer": "75119", "dragertype": "negatiefnr.", "technische_gegevens": "Materiaal: zw/w\nFilm     : 35mm\nGeluid   : CO", "dragerid": "1169194", "publid": "-1", "beginopdrager": 2266000}, {"datum_aangemaakt": "2008-04-11T23:30:09", "dragersoort": "Programma", "volgnummer": 1, "eindeopdrager": 2371000, "annotatie": "False", "positieid": "1541032", "dragernummer": "75-43", "dragertype": "wknr.", "technische_gegevens": "Materiaal: zw/w\nFilm     : 35mm\nGeluid   : CO", "dragerid": "1168102", "publid": "-1", "beginopdrager": 2266000}], "parent_id": "424312", "broncatalogus": "Polygoon Hollands Nieuws", "aanmaakdatum": "2013-11-24T06:14:56", "maker": [{"naam": "Bloemendal, Philip", "functies": ["commentaar"]}], "begintijd": 2266000, "niveaus": [{"geografische_namen": ["Nederland", "Duiven"], "trefwoorden": [{"trefwoord": "afval"}, {"trefwoord": "afvalverbranding"}, {"trefwoord": "vuilstortplaatsen"}], "taalID": "1", "themas": ["Tranche POL goedgekeurd"], "intentieID": "1", "collectie_avails": ["Polygoon Hollands Nieuws"], "beschrijving": "In Duiven is de eerste vuilverbrandings-installatie van\nOost-Nederland in gebruik gesteld.\nSHOTS: vuilniswagen stort afval, voornamelijk vuilniszakken,\nop vuilnisbelt; ext. verbrandingsinstallatie; vuilniswagens\nstorten afval in bunker; kraan tilt afval en kraanmachinist\nstort dit, visueel geholpen door monitoren waarop de\nverschillende delen van de ruimte te zien zijn, in de oven;\ncentrale controleruimte; vuilverbranding; vuilrestanten op\nlopende band, waarbij metalen middels een magneet van de rest\nworden gescheiden."}], "context": [{"kleur": "zw/w"}], "id": "391120", "laatst_aangepastdatum": "2014-05-08T15:02:49", "tijdsduur": 105000, "type": "Item", "opnamen": [{"annotatie": "(exacte datum onbekend)", "datumprecisie": "exacte datum onbekend", "begindatum": "01-01-1975"}], "verwijderd": false, "titel": {"tekst": "OPENING NIEUWE VUILVERBRANDINGSINSTALLATIE VOOR HET GEWEST\nARNHEM"}}], "facets": [], "reeks": {"aanmaakdatum": "2013-11-24T04:59:35", "aantalafleveringen": 0, "parent_id": "12070", "verwijderd": false, "id": "12070", "laatst_aangepastdatum": "2013-11-24T04:59:35"}, "realisatie": {"titel": {"tekst": "Polygoon Hollands Nieuws", "bron": "Avail TITEL", "type": "Titel"}, "distributiekanaal": "bioscoop", "aanmaakdatum": "2013-11-24T04:59:35", "overige_titels": [{"tekst": "polhn#Polygoon Hollands Nieuws", "bron": "Prodic", "type": "ProdicTitel"}], "parent_id": "12068", "niveaus": [{"genres": ["journaal"], "taalID": "1", "intentieID": "1", "samenvatting": "Bioscoopjournaals waarin Nederlandse onderwerpen van een bepaalde week worden gepresenteerd.", "deelcatalogi": ["Bewegend beeld/Polygoon/Hollands nieuws"], "taakID": "28573"}, {"beschrijving": "Het Polygoon-journaal is decennialang h\u00e9t bioscoopjournaal in Nederland. In januari 1922 beginnen de eerste wekelijkse filmjournaals onder de titel 'Hollandsch nieuws'. Tot 1986 blijft het Polygoonjournaal bestaan. Daarna stopt het, omdat het bioscoopjournaal definitief is 'ingehaald' door de dagelijkse televisiejournaals. Philip Bloemendal (1918-1999) is veertig jaar lang d\u00e9 stem van Polygoon.", "genres": ["Nieuws"], "taalID": "1", "taakID": "29772", "intentieID": "2"}], "laatst_aangepastdatum": "2013-11-24T04:59:35", "id": "12070", "verwijderd": false}, "werk": {"titel": {"tekst": "Polygoon bioscoopjournaal", "type": "uniforme titel"}, "aanmaakdatum": "2013-11-24T05:02:23", "overige_titels": [{"tekst": "polhn#Polygoon bioscoopjournaal", "bron": "Prodic", "type": "ProdicTitel"}], "niveaus": [{"taalID": "1", "taakID": "28553", "intentieID": "1"}], "laatst_aangepastdatum": "2013-11-24T05:02:23", "id": "12068", "verwijderd": false}}