{"expressie": {"titel": {"tekst": "Weeknummer 25-30"}, "publicaties": [{"distributiekanaal": "bioscoop", "sorteerdatum": "19-07-1925", "zendgemachtigden": ["NIET VAN TOEPASSING"], "ugstatus": "Onbekend", "weeknummer": "25-30", "sorteertype": "2", "type": "film", "id": "425501"}], "aanmaakdatum": "2013-11-24T06:12:44", "collecties_online": "ccbysa", "parent_id": "12070", "niveaus": [{"taakID": "521281", "taalID": "1", "themas": ["Tranche PHN goedgekeurd"], "intentieID": "1"}], "laatst_aangepastdatum": "2014-05-08T14:53:13", "id": "424556", "verwijderd": false}, "selecties": [{"eindtijd": 2562000, "docid": "670", "tijdsduur_annotatie": "Avail: 3'20\"", "posities": [{"datum_aangemaakt": "2008-04-11T23:30:09", "dragersoort": "Programma", "volgnummer": 1, "eindeopdrager": 2563000, "annotatie": "False", "positieid": "1542980", "dragernummer": "TDP27", "dragertype": "DIGI-BETA", "technische_gegevens": "Film: 35 mm brandbaar/ origineelnegatief NOB/ master RVD\nMateriaal: Zw/w\nGeluid: stom", "dragerid": "1159930", "publid": "-1", "beginopdrager": 2362400}, {"dragersoort": "Programma", "bewaarplaats": "Digitaal Archief", "dmguid": "2008011714350770800790450740014C2607C530000005168B00000D0F001804", "datum_aangemaakt": "2008-04-11T23:30:09", "sof": "2361000", "volgnummer": 1, "eindeopdrager": 2563000, "positieid": "2711604", "dragernummer": "WEEKNUMMER253-HRE0000C805", "dragertype": "media archive", "dragerid": "1814989", "publid": "-1", "beginopdrager": 2362400}, {"bewaarplaats": "Digitaal Archief", "datum_aangemaakt": "2008-04-11T23:30:09", "dragersoort": "Programma", "volgnummer": 1, "eindeopdrager": 2563000, "positieid": "2711323", "dragernummer": "WEEKNUMMER253-HRE0000C805.mpg", "dragertype": "MPG1", "dragerid": "1814667", "publid": "-1", "beginopdrager": 2362400}, {"bewaarplaats": "Digitaal Archief", "datum_aangemaakt": "2008-04-11T23:30:09", "dragersoort": "Programma", "volgnummer": 1, "eindeopdrager": 2563000, "positieid": "2711324", "dragernummer": "WEEKNUMMER253-HRE0000C805.mxf", "dragertype": "MXF", "dragerid": "1814668", "publid": "-1", "beginopdrager": 2362400}, {"datum_aangemaakt": "2008-04-11T23:30:09", "dragersoort": "Programma", "volgnummer": 1, "eindeopdrager": 2562000, "annotatie": "False", "positieid": "1542978", "dragernummer": "25280", "dragertype": "negatiefnr.", "technische_gegevens": "Film: 35 mm brandbaar/ origineelnegatief NOB/ master RVD\nMateriaal: Zw/w\nGeluid: stom", "dragerid": "1169413", "publid": "-1", "beginopdrager": 2362000}, {"datum_aangemaakt": "2008-04-11T23:30:09", "dragersoort": "Programma", "volgnummer": 1, "eindeopdrager": 2562000, "annotatie": "False", "positieid": "1542976", "dragernummer": "25-30", "dragertype": "wknr.", "technische_gegevens": "Film: 35 mm brandbaar/ origineelnegatief NOB/ master RVD\nMateriaal: Zw/w\nGeluid: stom", "dragerid": "1166637", "publid": "-1", "beginopdrager": 2362000}], "parent_id": "424556", "broncatalogus": "Polygoon Hollands Nieuws", "aanmaakdatum": "2013-11-24T06:09:18", "id": "391364", "begintijd": 2362000, "verwijderd": false, "context": [{"indicatie_stom": true, "kleur": "zw/w"}], "laatst_aangepastdatum": "2014-05-08T14:53:13", "tijdsduur": 200000, "type": "Item", "opnamen": [{"begindatum": "02-10-1925"}], "niveaus": [{"geografische_namen": ["Volendam", "Nederland"], "trefwoorden": [{"trefwoord": "consumptie-ijs"}, {"trefwoord": "kermissen"}, {"trefwoord": "klederdrachten"}, {"trefwoord": "lederindustrie"}, {"trefwoord": "ophaalbruggen"}], "taalID": "1", "themas": ["Tranche POL goedgekeurd"], "intentieID": "1", "collectie_avails": ["Polygoon Hollands Nieuws"], "annotatie": "RVD-nummer: 99-027", "beschrijving": "-vier mannen in Volendams kostuum op een bankje 8\";\n-diverse shots 2'48\" van kinderen en volwassenen in\nVolendamse klederdracht op de kermis: oa in draaimolen (27\"),\ncarrousel (close shots, in de carrousel 41\"), bij karretje\nvan een ijscoman (17\"), ijsetend (2x5\") en ballonnen\nopblazend (28\");\n-mediumshot 10\" en totaalshot 4\": groot gezelschap mannen\nvrouwen en kinderen in Volendamse klederdracht lopen\nophaalbrug over;\n-totaalshot 6\" gedeelte Volendamse kermis.", "vervallen_trefwoorden": ["ijscoman", "draaimolens"]}], "titel": {"tekst": "KERMIS"}}], "facets": [], "reeks": {"aanmaakdatum": "2013-11-24T04:59:35", "aantalafleveringen": 0, "parent_id": "12070", "verwijderd": false, "id": "12070", "laatst_aangepastdatum": "2013-11-24T04:59:35"}, "realisatie": {"titel": {"tekst": "Polygoon Hollands Nieuws", "bron": "Avail TITEL", "type": "Titel"}, "distributiekanaal": "bioscoop", "aanmaakdatum": "2013-11-24T04:59:35", "overige_titels": [{"tekst": "polhn#Polygoon Hollands Nieuws", "bron": "Prodic", "type": "ProdicTitel"}], "parent_id": "12068", "niveaus": [{"genres": ["journaal"], "taalID": "1", "intentieID": "1", "samenvatting": "Bioscoopjournaals waarin Nederlandse onderwerpen van een bepaalde week worden gepresenteerd.", "deelcatalogi": ["Bewegend beeld/Polygoon/Hollands nieuws"], "taakID": "28573"}, {"beschrijving": "Het Polygoon-journaal is decennialang h\u00e9t bioscoopjournaal in Nederland. In januari 1922 beginnen de eerste wekelijkse filmjournaals onder de titel 'Hollandsch nieuws'. Tot 1986 blijft het Polygoonjournaal bestaan. Daarna stopt het, omdat het bioscoopjournaal definitief is 'ingehaald' door de dagelijkse televisiejournaals. Philip Bloemendal (1918-1999) is veertig jaar lang d\u00e9 stem van Polygoon.", "genres": ["Nieuws"], "taalID": "1", "taakID": "29772", "intentieID": "2"}], "laatst_aangepastdatum": "2013-11-24T04:59:35", "id": "12070", "verwijderd": false}, "werk": {"titel": {"tekst": "Polygoon bioscoopjournaal", "type": "uniforme titel"}, "aanmaakdatum": "2013-11-24T05:02:23", "overige_titels": [{"tekst": "polhn#Polygoon bioscoopjournaal", "bron": "Prodic", "type": "ProdicTitel"}], "niveaus": [{"taalID": "1", "taakID": "28553", "intentieID": "1"}], "laatst_aangepastdatum": "2013-11-24T05:02:23", "id": "12068", "verwijderd": false}}