{"expressie": {"titel": {"tekst": "Weeknummer 62-17"}, "publicaties": [{"distributiekanaal": "bioscoop", "sorteerdatum": "23-04-1962", "zendgemachtigden": ["NIET VAN TOEPASSING"], "ugstatus": "Onbekend", "weeknummer": "62-17", "sorteertype": "2", "type": "film", "id": "429074"}], "aanmaakdatum": "2013-11-24T05:52:20", "collecties_online": "ccbysa", "parent_id": "12070", "niveaus": [{"taakID": "524854", "taalID": "1", "themas": ["Tranche PHN goedgekeurd"], "intentieID": "1"}], "laatst_aangepastdatum": "2014-05-08T15:03:46", "id": "428129", "verwijderd": false}, "selecties": [{"eindtijd": 3282000, "docid": "15855", "tijdsduur_annotatie": "Avail: 3'01\"  (86 mtr.)", "posities": [{"datum_aangemaakt": "2008-04-11T23:30:09", "dragersoort": "Programma", "volgnummer": 1, "eindeopdrager": 3283000, "annotatie": "False", "positieid": "1568883", "dragernummer": "TDP352", "dragertype": "DIGI-BETA", "technische_gegevens": "Materiaal: zw/w\nFilm     : 35mm\nGeluid   : CO", "dragerid": "41818", "publid": "-1", "beginopdrager": 3100000}, {"dragersoort": "Programma", "bewaarplaats": "Digitaal Archief", "dmguid": "2009052620114920800790450740014C2607C530000005848B00000D0F001316", "datum_aangemaakt": "2009-05-26T20:14:02", "sof": "3100000", "volgnummer": 1, "eindeopdrager": 3283000, "positieid": "28837316", "dragernummer": "WEEKNUMMER621-HRE0001C273", "dragertype": "media archive", "dragerid": "2816005", "publid": "-1", "beginopdrager": 3100000}, {"bewaarplaats": "Digitaal Archief", "datum_aangemaakt": "2009-05-26T16:58:40", "dragersoort": "Programma", "volgnummer": 1, "eindeopdrager": 3283000, "positieid": "28769117", "dragernummer": "WEEKNUMMER621-HRE0001C273.mpg", "dragertype": "MPG1", "dragerid": "2815716", "publid": "-1", "beginopdrager": 3100000}, {"bewaarplaats": "Digitaal Archief", "datum_aangemaakt": "2009-05-26T16:58:40", "dragersoort": "Programma", "volgnummer": 1, "eindeopdrager": 3283000, "positieid": "28769118", "dragernummer": "WEEKNUMMER621-HRE0001C273.mxf", "dragertype": "MXF", "dragerid": "2815717", "publid": "-1", "beginopdrager": 3100000}, {"bewaarplaats": "BenG storage 1", "datum_aangemaakt": "2011-07-20T19:18:58", "dragersoort": "Programma", "volgnummer": 1, "eindeopdrager": 3283000, "positieid": "89738738", "dragernummer": "WEEKNUMMER621-HRE0001C273.mxf", "dragertype": "MXF", "dragerid": "7370576", "publid": "-1", "beginopdrager": 3100000}, {"datum_aangemaakt": "2008-04-11T23:30:09", "dragersoort": "Programma", "volgnummer": 1, "eindeopdrager": 3282000, "annotatie": "False", "positieid": "1568881", "dragernummer": "62110", "dragertype": "negatiefnr.", "technische_gegevens": "Materiaal: zw/w\nFilm     : 35mm\nGeluid   : CO", "dragerid": "1171676", "publid": "-1", "beginopdrager": 3101000}, {"datum_aangemaakt": "2008-04-11T23:30:09", "dragersoort": "Programma", "volgnummer": 1, "eindeopdrager": 3282000, "annotatie": "False", "positieid": "1568879", "dragernummer": "62-17", "dragertype": "wknr.", "technische_gegevens": "Materiaal: zw/w\nFilm     : 35mm\nGeluid   : CO", "dragerid": "1157766", "publid": "-1", "beginopdrager": 3101000}], "parent_id": "428129", "broncatalogus": "Polygoon Hollands Nieuws", "aanmaakdatum": "2013-11-24T05:48:53", "maker": [{"naam": "Bloemendal, Philip", "functies": ["commentaar"]}], "begintijd": 3101000, "niveaus": [{"geografische_namen": ["Nederland", "Zevenaar", "Noordrijn-Westfalen", "West-Duitsland", "A12", "Elten"], "trefwoorden": [{"trefwoord": "openingen"}, {"trefwoord": "snelwegen"}], "persoonsnamen": ["Korthals, H.A."], "taalID": "1", "themas": ["Tranche POL goedgekeurd"], "intentieID": "1", "collectie_avails": ["Polygoon Hollands Nieuws"], "beschrijving": "Drs. H.A. Korthals, minister van Verkeer en Waterstaat, opent\nhet laatste deel van de Rijksweg A12 (E36) tussen Zevenaar en\nde Duitse grens naar Emmerich. Bij het nieuwe douanekantoor\nschudden hij en zijn collega minister Erkens van\nNoordrijn-Westfalen elkaar de hand. De op- en afritten van de\nnu nog over Nederlands grondgebied lopende weg zijn tijdelijk\nafgesloten met betonpalen, om het omzeilen van de duoane te\nvoorkomen. Verder beelden van de oude route door het centrum\nvan Zevenaar, via een smalle bochtige weg met drukke\nspoorwegovergangen, en door het centrum van het nog onder\nNederlands bestuur staande drostambt Elten met de\nNederlands-Duitse douanepost."}], "context": [{"kleur": "zw/w"}], "id": "394936", "laatst_aangepastdatum": "2014-05-08T15:03:47", "tijdsduur": 181000, "type": "Item", "opnamen": [{"annotatie": "1962-04-13", "begindatum": "11-04-1962"}], "verwijderd": false, "titel": {"tekst": "WEGVERBINDING MET DUITSLAND VERBETERD"}}], "facets": [], "reeks": {"aanmaakdatum": "2013-11-24T04:59:35", "aantalafleveringen": 0, "parent_id": "12070", "verwijderd": false, "id": "12070", "laatst_aangepastdatum": "2013-11-24T04:59:35"}, "realisatie": {"titel": {"tekst": "Polygoon Hollands Nieuws", "bron": "Avail TITEL", "type": "Titel"}, "distributiekanaal": "bioscoop", "aanmaakdatum": "2013-11-24T04:59:35", "overige_titels": [{"tekst": "polhn#Polygoon Hollands Nieuws", "bron": "Prodic", "type": "ProdicTitel"}], "parent_id": "12068", "niveaus": [{"genres": ["journaal"], "taalID": "1", "intentieID": "1", "samenvatting": "Bioscoopjournaals waarin Nederlandse onderwerpen van een bepaalde week worden gepresenteerd.", "deelcatalogi": ["Bewegend beeld/Polygoon/Hollands nieuws"], "taakID": "28573"}, {"beschrijving": "Het Polygoon-journaal is decennialang h\u00e9t bioscoopjournaal in Nederland. In januari 1922 beginnen de eerste wekelijkse filmjournaals onder de titel 'Hollandsch nieuws'. Tot 1986 blijft het Polygoonjournaal bestaan. Daarna stopt het, omdat het bioscoopjournaal definitief is 'ingehaald' door de dagelijkse televisiejournaals. Philip Bloemendal (1918-1999) is veertig jaar lang d\u00e9 stem van Polygoon.", "genres": ["Nieuws"], "taalID": "1", "taakID": "29772", "intentieID": "2"}], "laatst_aangepastdatum": "2013-11-24T04:59:35", "id": "12070", "verwijderd": false}, "werk": {"titel": {"tekst": "Polygoon bioscoopjournaal", "type": "uniforme titel"}, "aanmaakdatum": "2013-11-24T05:02:23", "overige_titels": [{"tekst": "polhn#Polygoon bioscoopjournaal", "bron": "Prodic", "type": "ProdicTitel"}], "niveaus": [{"taalID": "1", "taakID": "28553", "intentieID": "1"}], "laatst_aangepastdatum": "2013-11-24T05:02:23", "id": "12068", "verwijderd": false}}