{"expressie": {"publicaties": [{"distributiekanaal": "niet van toepassing", "zendgemachtigden": ["NIET VAN TOEPASSING"], "ugstatus": "Onbekend", "sorteertype": "0", "type": "niet van toepassing", "id": "3638191"}, {"distributiekanaal": "bioscoop", "sorteerdatum": "16-01-1961", "zendgemachtigden": ["NIET VAN TOEPASSING"], "ugstatus": "Onbekend", "weeknummer": "61-04", "sorteertype": "2", "type": "film", "id": "423101"}], "posities": [{"datum_aangemaakt": "2009-07-31T12:54:54", "dragersoort": "Programma", "opbergeenheid": "000700-001", "dragerannotatie": "00:00:00 = eerste beeld van eerste item op rol", "geluidstype": "com opt", "formaat": "16 mm", "annotatie": "False", "positieid": "43677139", "dragernummer": "000700-001", "dragertype": "FILM", "technische_gegevens": "FILM: 16mm zw/w opt.gel\nEngelse ondertiteling", "depotstatus": "in depot", "dragerid": "2992434", "publid": "3638191", "locatie": "4", "archiefstatus": "veiligstelling materiaal"}], "aanmaakdatum": "2013-11-24T06:25:24", "collecties_online": "ccbysa", "parent_id": "12070", "niveaus": [{"taakID": "518881", "taalID": "1", "themas": ["Tranche PHN goedgekeurd"], "intentieID": "1"}], "laatst_aangepastdatum": "2014-05-08T15:02:20", "id": "422156", "verwijderd": false, "titel": {"tekst": "Weeknummer 61-04"}}, "selecties": [{"eindtijd": 2144000, "docid": "15297", "tijdsduur_annotatie": "Avail: 1'41\" (49 mtr.)", "posities": [{"datum_aangemaakt": "2008-04-11T23:30:09", "dragersoort": "Programma", "volgnummer": 1, "eindeopdrager": 2145000, "annotatie": "False", "positieid": "1525078", "dragernummer": "TDP338", "dragertype": "DIGI-BETA", "technische_gegevens": "Materiaal: zw/w\nFilm     : 35mm\nGeluid   : CO", "dragerid": "41393", "publid": "-1", "beginopdrager": 2042360}, {"datum_aangemaakt": "2009-07-31T12:54:54", "dragersoort": "Programma", "volgnummer": 2, "locatie": "4", "opbergeenheid": "000700-001", "dragerannotatie": "00:00:00 = eerste beeld van eerste item op rol", "geluidstype": "com opt", "formaat": "16 mm", "annotatie": "False", "positieid": "43677140", "dragernummer": "000700-001", "dragertype": "FILM", "technische_gegevens": "FILM: 16mm zw/w opt.gel\nEngelse ondertiteling", "depotstatus": "in depot", "dragerid": "2992434", "publid": "-1", "beginopdrager": 1350000, "eindeopdrager": 1455000, "archiefstatus": "veiligstelling materiaal"}, {"dragersoort": "Programma", "bewaarplaats": "Digitaal Archief", "dmguid": "2009063013001090800790450740014C2607C530000003932B00000D0F002443", "datum_aangemaakt": "2009-06-30T13:03:49", "sof": "2042000", "volgnummer": 1, "eindeopdrager": 2145000, "positieid": "34158895", "dragernummer": "WEEKNUMMER610-HRE0001DC1A", "dragertype": "media archive", "dragerid": "2861810", "publid": "-1", "beginopdrager": 2042360}, {"bewaarplaats": "Digitaal Archief", "datum_aangemaakt": "2009-06-30T04:09:33", "dragersoort": "Programma", "volgnummer": 1, "eindeopdrager": 2145000, "positieid": "34157398", "dragernummer": "WEEKNUMMER610-HRE0001DC1A.mpg", "dragertype": "MPG1", "dragerid": "2860540", "publid": "-1", "beginopdrager": 2042360}, {"bewaarplaats": "BenG storage 1", "datum_aangemaakt": "2011-08-30T22:08:51", "dragersoort": "Programma", "volgnummer": 1, "eindeopdrager": 2145000, "positieid": "90007813", "dragernummer": "WEEKNUMMER610-HRE0001DC1A.mxf", "dragertype": "MXF", "dragerid": "7623663", "publid": "-1", "beginopdrager": 2042360}, {"bewaarplaats": "Digitaal Archief", "datum_aangemaakt": "2009-06-30T04:09:33", "dragersoort": "Programma", "volgnummer": 1, "eindeopdrager": 2145000, "positieid": "34157399", "dragernummer": "WEEKNUMMER610-HRE0001DC1A.mxf", "dragertype": "MXF", "dragerid": "2860541", "publid": "-1", "beginopdrager": 2042360}, {"datum_aangemaakt": "2008-04-11T23:30:09", "dragersoort": "Programma", "volgnummer": 1, "eindeopdrager": 2144000, "annotatie": "False", "positieid": "1525076", "dragernummer": "61019", "dragertype": "negatiefnr.", "technische_gegevens": "Materiaal: zw/w\nFilm     : 35mm\nGeluid   : CO", "dragerid": "1167618", "publid": "-1", "beginopdrager": 2043000}, {"datum_aangemaakt": "2008-04-11T23:30:09", "dragersoort": "Programma", "volgnummer": 1, "eindeopdrager": 2144000, "annotatie": "False", "positieid": "1525074", "dragernummer": "61-04", "dragertype": "wknr.", "technische_gegevens": "Materiaal: zw/w\nFilm     : 35mm\nGeluid   : CO", "dragerid": "1158418", "publid": "-1", "beginopdrager": 2043000}], "parent_id": "422156", "broncatalogus": "Polygoon Hollands Nieuws", "aanmaakdatum": "2013-11-24T06:25:24", "maker": [{"naam": "Bloemendal, Philip", "functies": ["commentaar"]}], "begintijd": 2043000, "niveaus": [{"geografische_namen": ["Nederland", "Maastricht"], "trefwoorden": [{"trefwoord": "kunstacademies"}, {"trefwoord": "openingen"}], "persoonsnamen": ["Levigne, Hub", "Moors, P.J.A.", "Scholten, Ynso"], "namen": ["Jan van Eyck Academie"], "taalID": "1", "themas": ["Tranche POL goedgekeurd"], "intentieID": "1", "collectie_avails": ["Polygoon Hollands Nieuws"], "beschrijving": "Offici\u00eble opening van het nieuwe gebouw van de Jan van Eyck\nAcademie te Maastricht, ontworpen door architect Peutz.\nMonseigneur P. Moors, bisschop van Roermond, zegent het\ngebouw in, waarna mr. Ynso Scholten, staatssecretaris van\nOKW, de menigte toespreekt. De graficus prof. Hub Levigne\ngeeft les op de grafeer- en etsafdeling, oa in steendrukken\nen lithografie. Verder schilderen studenten een model."}], "context": [{"kleur": "zw/w"}], "id": "388964", "laatst_aangepastdatum": "2014-05-08T15:02:20", "tijdsduur": 101000, "type": "Item", "opnamen": [{"annotatie": "1961-01-16", "begindatum": "14-01-1961"}], "verwijderd": false, "titel": {"tekst": "OPENING VAN JAN VAN EYCK ACADEMIE IN MAASTRICHT"}}], "facets": [], "reeks": {"aanmaakdatum": "2013-11-24T04:59:35", "aantalafleveringen": 0, "parent_id": "12070", "verwijderd": false, "id": "12070", "laatst_aangepastdatum": "2013-11-24T04:59:35"}, "realisatie": {"titel": {"tekst": "Polygoon Hollands Nieuws", "bron": "Avail TITEL", "type": "Titel"}, "distributiekanaal": "bioscoop", "aanmaakdatum": "2013-11-24T04:59:35", "overige_titels": [{"tekst": "polhn#Polygoon Hollands Nieuws", "bron": "Prodic", "type": "ProdicTitel"}], "parent_id": "12068", "niveaus": [{"genres": ["journaal"], "taalID": "1", "intentieID": "1", "samenvatting": "Bioscoopjournaals waarin Nederlandse onderwerpen van een bepaalde week worden gepresenteerd.", "deelcatalogi": ["Bewegend beeld/Polygoon/Hollands nieuws"], "taakID": "28573"}, {"beschrijving": "Het Polygoon-journaal is decennialang h\u00e9t bioscoopjournaal in Nederland. In januari 1922 beginnen de eerste wekelijkse filmjournaals onder de titel 'Hollandsch nieuws'. Tot 1986 blijft het Polygoonjournaal bestaan. Daarna stopt het, omdat het bioscoopjournaal definitief is 'ingehaald' door de dagelijkse televisiejournaals. Philip Bloemendal (1918-1999) is veertig jaar lang d\u00e9 stem van Polygoon.", "genres": ["Nieuws"], "taalID": "1", "taakID": "29772", "intentieID": "2"}], "laatst_aangepastdatum": "2013-11-24T04:59:35", "id": "12070", "verwijderd": false}, "werk": {"titel": {"tekst": "Polygoon bioscoopjournaal", "type": "uniforme titel"}, "aanmaakdatum": "2013-11-24T05:02:23", "overige_titels": [{"tekst": "polhn#Polygoon bioscoopjournaal", "bron": "Prodic", "type": "ProdicTitel"}], "niveaus": [{"taalID": "1", "taakID": "28553", "intentieID": "1"}], "laatst_aangepastdatum": "2013-11-24T05:02:23", "id": "12068", "verwijderd": false}}