{"expressie": {"publicaties": [{"distributiekanaal": "bioscoop", "technische_annotatie": "Materiaal: zw/w\nFilm     : 35mm\nGeluid   : CO", "sorteerdatum": "25-06-1979", "zendgemachtigden": ["NIET VAN TOEPASSING"], "ugstatus": "Onbekend", "weeknummer": "79-26", "sorteertype": "2", "type": "film", "id": "19532", "tijdsduur": 167080}], "posities": [{"datum_aangemaakt": "2008-04-11T23:30:09", "dragersoort": "Programma", "eindeopdrager": 1753280, "annotatie": "False", "positieid": "563506", "dragernummer": "TDP466", "dragertype": "DIGI-BETA", "technische_gegevens": "Materiaal: zw/w\nFilm     : 35mm\nGeluid   : CO", "depotstatus": "in depot", "dragerid": "52011", "publid": "19532", "beginopdrager": 1586160}, {"dragersoort": "Programma", "bewaarplaats": "Digitaal Archief", "dmguid": "444C4755494400FA26E2EC1D392700B5C3C88B030103000BE1A8C0DC24000000", "datum_aangemaakt": "2008-04-11T23:30:09", "sof": "1586160", "volgnummer": 1, "eindeopdrager": 1753280, "annotatie": "False", "positieid": "563509", "dragernummer": "WEEKNUMMER792-HRE00004CF7", "dragertype": "media archive", "technische_gegevens": "Materiaal: zw/w\nFilm     : 35mm\nGeluid   : CO", "dragerannotatie": "BG_10641.mpg", "dragerid": "54983", "publid": "19532", "beginopdrager": 1586160}, {"bewaarplaats": "Digitaal Archief", "datum_aangemaakt": "2008-04-11T23:30:09", "dragersoort": "Programma", "eindeopdrager": 1753280, "annotatie": "False", "positieid": "563507", "dragernummer": "BG_10641.mpg", "dragertype": "MPG1", "technische_gegevens": "Materiaal: zw/w\nFilm     : 35mm\nGeluid   : CO", "dragerid": "54985", "publid": "19532", "beginopdrager": 1586160}, {"bewaarplaats": "Digitaal Archief", "datum_aangemaakt": "2008-04-11T23:30:09", "dragersoort": "Programma", "eindeopdrager": 1753280, "annotatie": "False", "positieid": "563503", "dragernummer": "WEEKNUMMER792-HRE00004CF7.mxf", "dragertype": "MXF", "technische_gegevens": "Materiaal: zw/w\nFilm     : 35mm\nGeluid   : CO", "dragerid": "137213", "publid": "19532", "beginopdrager": 1586160}, {"datum_aangemaakt": "2008-04-11T23:30:09", "dragersoort": "Programma", "eindeopdrager": 1753280, "annotatie": "False", "positieid": "563505", "dragernummer": "79153", "dragertype": "negatiefnr.", "technische_gegevens": "Materiaal: zw/w\nFilm     : 35mm\nGeluid   : CO", "dragerid": "54986", "publid": "19532", "beginopdrager": 1586160}, {"datum_aangemaakt": "2008-04-11T23:30:09", "dragersoort": "Programma", "eindeopdrager": 1753280, "annotatie": "False", "positieid": "563508", "dragernummer": "79-26", "dragertype": "wknr.", "technische_gegevens": "Materiaal: zw/w\nFilm     : 35mm\nGeluid   : CO", "dragerid": "54528", "publid": "19532", "beginopdrager": 1586160}, {"bewaarplaats": "OnderwijsStorage", "datum_aangemaakt": "2008-04-11T23:30:09", "dragersoort": "Programma", "eindeopdrager": 1753280, "annotatie": "False", "positieid": "1396721", "dragernummer": "BG_10641.wmv", "dragertype": "WMV", "technische_gegevens": "Materiaal: zw/w\nFilm     : 35mm\nGeluid   : CO", "dragerid": "1152456", "publid": "19532", "beginopdrager": 1586160}], "aanmaakdatum": "2013-11-24T05:00:20", "collecties_online": "ccbysa", "parent_id": "12070", "niveaus": [{"taalID": "1", "taakID": "33544", "intentieID": "1"}, {"taalID": "1", "themas": ["Medialounge / Medialounge / diversen"], "intentieID": "2", "samenvatting": "De VAM bestaat vijftig jaar.", "taakID": "33545", "beschrijving": "De VAM bestaat vijftig jaar: de Vuil Afvoer Maatschappij in het Drentse Wijster verwerkt jaarlijks een miljoen ton huisvuil uit 130 gemeenten.\n\nCompost\nEen lange trein met vuilcontainers brengt het afval naar Wijster, waar het een bewerking krijgt tot compost."}], "laatst_aangepastdatum": "2014-05-08T14:55:56", "tijdsduur": 167080, "id": "19532", "verwijderd": false, "titel": {"tekst": "Weeknummer 79-26", "type": "Titel"}}, "selecties": [{"docid": "20412", "titel": {"tekst": "DE VUIL AFVOER MAATSCHAPPIJ BESTAAT VIJFTIG JAAR", "bron": "Avail TITEL", "type": "Titel"}, "posities": [{"datum_aangemaakt": "2008-04-11T23:30:09", "dragersoort": "Programma", "eindeopdrager": 1753000, "annotatie": "False", "positieid": "1112266", "dragernummer": "TDP466", "dragertype": "DIGI-BETA", "technische_gegevens": "Materiaal: zw/w\nFilm     : 35mm\nGeluid   : CO", "depotstatus": "in depot", "dragerid": "52011", "publid": "-1", "beginopdrager": 1586000}, {"dragersoort": "Programma", "bewaarplaats": "Digitaal Archief", "dmguid": "444C4755494400FA26E2EC1D392700B5C3C88B030103000BE1A8C0DC24000000", "sortering": "1", "datum_aangemaakt": "2008-04-11T23:30:09", "sof": "1586160", "volgnummer": 1, "eindeopdrager": 1753000, "annotatie": "False", "positieid": "1112263", "dragernummer": "WEEKNUMMER792-HRE00004CF7", "dragertype": "media archive", "technische_gegevens": "Materiaal: zw/w\nFilm     : 35mm\nGeluid   : CO", "dragerannotatie": "BG_10641.mpg", "dragerid": "54983", "publid": "-1", "beginopdrager": 1586000}, {"bewaarplaats": "Digitaal Archief", "datum_aangemaakt": "2008-04-11T23:30:09", "dragersoort": "Programma", "eindeopdrager": 1753000, "annotatie": "False", "positieid": "1112265", "dragernummer": "BG_10641.mpg", "dragertype": "MPG1", "technische_gegevens": "Materiaal: zw/w\nFilm     : 35mm\nGeluid   : CO", "dragerid": "54985", "publid": "-1", "beginopdrager": 1586000}, {"bewaarplaats": "Digitaal Archief", "datum_aangemaakt": "2008-04-11T23:30:09", "dragersoort": "Programma", "eindeopdrager": 1753000, "annotatie": "False", "positieid": "1112269", "dragernummer": "WEEKNUMMER792-HRE00004CF7.mxf", "dragertype": "MXF", "technische_gegevens": "Materiaal: zw/w\nFilm     : 35mm\nGeluid   : CO", "dragerid": "137213", "publid": "-1", "beginopdrager": 1586000}, {"datum_aangemaakt": "2008-04-11T23:30:09", "dragersoort": "Programma", "eindeopdrager": 1753000, "annotatie": "False", "positieid": "1112267", "dragernummer": "79153", "dragertype": "negatiefnr.", "technische_gegevens": "Materiaal: zw/w\nFilm     : 35mm\nGeluid   : CO", "dragerid": "54986", "publid": "-1", "beginopdrager": 1586000}, {"datum_aangemaakt": "2008-04-11T23:30:09", "dragersoort": "Programma", "eindeopdrager": 1753000, "annotatie": "False", "positieid": "1112264", "dragernummer": "79-26", "dragertype": "wknr.", "technische_gegevens": "Materiaal: zw/w\nFilm     : 35mm\nGeluid   : CO", "dragerid": "54528", "publid": "-1", "beginopdrager": 1586000}], "broncatalogus": "Polygoon Hollands Nieuws", "aanmaakdatum": "2013-11-24T05:03:47", "opnamen": [{"datumprecisie": "exacte datum onbekend", "begindatum": "01-01-1979"}], "parent_id": "19532", "verwijderd": false, "laatst_aangepastdatum": "2014-05-08T14:55:56", "type": "Item", "id": "16652", "niveaus": [{"geografische_namen": ["Nederland"], "trefwoorden": [{"trefwoord": "afval"}, {"trefwoord": "afvalverwerking"}, {"trefwoord": "compost"}, {"trefwoord": "reinigingsdiensten"}, {"trefwoord": "vuilstortplaatsen"}], "namen": ["VAM"], "taalID": "1", "intentieID": "1", "collectie_avails": ["Polygoon Hollands Nieuws"], "annotatie": "Avail: 2'47\" (80 mtr.)", "beschrijving": "Aandacht voor de verwerking van huisvuil in Nederland i.v.m. het vijftigjarig bestaan van de VAM, die in circa 130 gemeenten jaarlijks een miljoen ton huisvuil verwerkt.\nSHOTS: vuilnisman gooit vuilniszakken in vuilniswagen; meeuwen vliegen rond vuilnisbelt; bulldozer plet huisvuil en bedekt het met een laag zand (waarna het gebied volgens de commentator \"uitstekend geschikt voor recreatie\" is); vuilverbrandingsoven; plaatje in boek van een ophaalwagen voor huisvuil uit 1929; trein met VAM-containers stort afval langs het spoor; vuilnis wordt automatisch natgespoten ter bevordering van de activiteit van microben; afval dat na enige tijd is geworden tot compost wordt met een grijper van een hijskraan via een trechter in een container gegooid; lopende banden met compost en het daaruit gefilterde niet verteerbare afval."}], "tijdsduur": 167000}], "facets": [], "reeks": {"aanmaakdatum": "2013-11-24T04:59:35", "aantalafleveringen": 0, "parent_id": "12070", "verwijderd": false, "id": "12070", "laatst_aangepastdatum": "2013-11-24T04:59:35"}, "keyframesets": [{"epguid": "2fd693ea-f7d7-49f6-8ae6-8946115596f9", "dmguid": "444C4755494400FA26E2EC1D392700B5C3C88B030103000BE1A8C0DC24000000", "numberOfKeyframes": 140, "timecodes": [0, 400, 440, 760, 1560, 1600, 4040, 4080, 6840, 6880, 8920, 8960, 13160, 15120, 15160, 17800, 18400, 18680, 22080, 22120, 26000, 26120, 27880, 30800, 30840, 39880, 41320, 41520, 43360, 45760, 45800, 50600, 50640, 55960, 57040, 59760, 59840, 59920, 60360, 60400, 60560, 60640, 60840, 60880, 63600, 64960, 68560, 68600, 70400, 71360, 71760, 72680, 73480, 73640, 77680, 77720, 78080, 78280, 78320, 78760, 78800, 79040, 79240, 79440, 79560, 79720, 80000, 80080, 80200, 80600, 80640, 80920, 81280, 81320, 82200, 82920, 82960, 85120, 85440, 86120, 89120, 89160, 91160, 91200, 93160, 93200, 95160, 95200, 97640, 101000, 101040, 102440, 106000, 106040, 107880, 108200, 108280, 108400, 108960, 109560, 110400, 113560, 113600, 116960, 117000, 117640, 118120, 118160, 122040, 122080, 124800, 128400, 128440, 130200, 134960, 135000, 137280, 138960, 139200, 139320, 140800, 140840, 141760, 143440, 146960, 148400, 149360, 151600, 151720, 151800, 155760, 158440, 159200, 161360, 161480, 161560, 161600, 163200, 163320, 167080]}], "realisatie": {"titel": {"tekst": "Polygoon Hollands Nieuws", "bron": "Avail TITEL", "type": "Titel"}, "distributiekanaal": "bioscoop", "aanmaakdatum": "2013-11-24T04:59:35", "overige_titels": [{"tekst": "polhn#Polygoon Hollands Nieuws", "bron": "Prodic", "type": "ProdicTitel"}], "parent_id": "12068", "niveaus": [{"genres": ["journaal"], "taalID": "1", "intentieID": "1", "samenvatting": "Bioscoopjournaals waarin Nederlandse onderwerpen van een bepaalde week worden gepresenteerd.", "deelcatalogi": ["Bewegend beeld/Polygoon/Hollands nieuws"], "taakID": "28573"}, {"beschrijving": "Het Polygoon-journaal is decennialang h\u00e9t bioscoopjournaal in Nederland. In januari 1922 beginnen de eerste wekelijkse filmjournaals onder de titel 'Hollandsch nieuws'. Tot 1986 blijft het Polygoonjournaal bestaan. Daarna stopt het, omdat het bioscoopjournaal definitief is 'ingehaald' door de dagelijkse televisiejournaals. Philip Bloemendal (1918-1999) is veertig jaar lang d\u00e9 stem van Polygoon.", "genres": ["Nieuws"], "taalID": "1", "taakID": "29772", "intentieID": "2"}], "laatst_aangepastdatum": "2013-11-24T04:59:35", "id": "12070", "verwijderd": false}, "werk": {"titel": {"tekst": "Polygoon bioscoopjournaal", "type": "uniforme titel"}, "aanmaakdatum": "2013-11-24T05:02:23", "overige_titels": [{"tekst": "polhn#Polygoon bioscoopjournaal", "bron": "Prodic", "type": "ProdicTitel"}], "niveaus": [{"taalID": "1", "taakID": "28553", "intentieID": "1"}], "laatst_aangepastdatum": "2013-11-24T05:02:23", "id": "12068", "verwijderd": false}}