{"expressie": {"titel": {"tekst": "Weeknummer 74-53"}, "publicaties": [{"distributiekanaal": "bioscoop", "sorteerdatum": "30-12-1974", "zendgemachtigden": ["NIET VAN TOEPASSING"], "ugstatus": "Onbekend", "weeknummer": "74-53", "sorteertype": "2", "type": "film", "id": "417189"}], "aanmaakdatum": "2013-11-24T07:03:51", "collecties_online": "ccbysa", "parent_id": "12070", "niveaus": [{"taakID": "512963", "taalID": "1", "themas": ["Tranche PHN goedgekeurd"], "intentieID": "1"}], "laatst_aangepastdatum": "2014-05-08T14:52:41", "id": "416245", "verwijderd": false}, "selecties": [{"eindtijd": 1096000, "docid": "20113", "tijdsduur_annotatie": "Avail: 1'31\" (43 mtr.)", "posities": [{"datum_aangemaakt": "2008-04-11T23:30:09", "dragersoort": "Programma", "volgnummer": 1, "eindeopdrager": 1097000, "annotatie": "False", "positieid": "1481750", "dragernummer": "TDP437", "dragertype": "DIGI-BETA", "technische_gegevens": "Materiaal: zw/w\nFilm     : 35mm\nGeluid   : CO", "dragerid": "55341", "publid": "-1", "beginopdrager": 1004880}, {"dragersoort": "Programma", "bewaarplaats": "Digitaal Archief", "dmguid": "2009051114472470800790450740014C2607C530000006620B00000D0F000712", "datum_aangemaakt": "2009-05-11T14:51:16", "sof": "1004000", "volgnummer": 1, "eindeopdrager": 1097000, "positieid": "21121648", "dragernummer": "WEEKNUMMER745-HRE0001B838", "dragertype": "media archive", "dragerid": "2789751", "publid": "-1", "beginopdrager": 1004880}, {"bewaarplaats": "Digitaal Archief", "datum_aangemaakt": "2009-05-11T13:24:16", "dragersoort": "Programma", "volgnummer": 1, "eindeopdrager": 1097000, "positieid": "21093987", "dragernummer": "WEEKNUMMER745-HRE0001B838.mpg", "dragertype": "MPG1", "dragerid": "2789562", "publid": "-1", "beginopdrager": 1004880}, {"bewaarplaats": "Digitaal Archief", "datum_aangemaakt": "2009-05-11T13:24:16", "dragersoort": "Programma", "volgnummer": 1, "eindeopdrager": 1097000, "positieid": "21093990", "dragernummer": "WEEKNUMMER745-HRE0001B838.mxf", "dragertype": "MXF", "dragerid": "2789563", "publid": "-1", "beginopdrager": 1004880}, {"bewaarplaats": "BenG storage 1", "datum_aangemaakt": "2011-07-20T06:22:45", "dragersoort": "Programma", "volgnummer": 1, "eindeopdrager": 1097000, "positieid": "89733846", "dragernummer": "WEEKNUMMER745-HRE0001B838.mxf", "dragertype": "MXF", "dragerid": "7367344", "publid": "-1", "beginopdrager": 1004880}, {"datum_aangemaakt": "2008-04-11T23:30:09", "dragersoort": "Programma", "volgnummer": 1, "eindeopdrager": 1096000, "annotatie": "False", "positieid": "1481748", "dragernummer": "74174", "dragertype": "negatiefnr.", "technische_gegevens": "Materiaal: zw/w\nFilm     : 35mm\nGeluid   : CO", "dragerid": "1163484", "publid": "-1", "beginopdrager": 1005000}, {"datum_aangemaakt": "2008-04-11T23:30:09", "dragersoort": "Programma", "volgnummer": 1, "eindeopdrager": 1096000, "annotatie": "False", "positieid": "1481746", "dragernummer": "74-53", "dragertype": "wknr.", "technische_gegevens": "Materiaal: zw/w\nFilm     : 35mm\nGeluid   : CO", "dragerid": "1163483", "publid": "-1", "beginopdrager": 1005000}], "parent_id": "416245", "broncatalogus": "Polygoon Hollands Nieuws", "aanmaakdatum": "2013-11-24T07:00:25", "maker": [{"naam": "Bloemendal, Philip", "functies": ["commentaar"]}], "begintijd": 1005000, "niveaus": [{"geografische_namen": ["Nederland", "Amsterdam"], "trefwoorden": [{"trefwoord": "kleding"}, {"trefwoord": "veilingen"}], "namen": ["Mak van Waay"], "taalID": "1", "themas": ["Tranche POL goedgekeurd"], "intentieID": "1", "collectie_avails": ["Polygoon Hollands Nieuws"], "beschrijving": "Er bestaat weer grote interesse voor de mode uit de jaren\n'20, de zogenaamde 'oma-jurken'. Bij een kunstveiling van Mak\nvan Waay in Amsterdam werd een collectie originele\ndameskleding uit de jaren '20 uit het bezit van mevrouw\nCanter Cremers-Van der Does onder grote belangstelling\ngeveild.\nSHOTS: etalage met 'oma-jurken'; veilingpersoneel toont\ndameskleding van mevrouw Canter Cremers; cu mevrouw Canter\nCremers; modellen in oude jurken; het bieden op een jurk."}], "context": [{"kleur": "zw/w"}], "id": "383062", "laatst_aangepastdatum": "2014-05-08T14:52:41", "tijdsduur": 91000, "type": "Item", "opnamen": [{"annotatie": "(exacte datum onbekend)", "datumprecisie": "exacte datum onbekend", "begindatum": "01-01-1974"}], "verwijderd": false, "titel": {"tekst": "OMA'S JURKEN ONDER DE HAMER"}}], "facets": [], "reeks": {"aanmaakdatum": "2013-11-24T04:59:35", "aantalafleveringen": 0, "parent_id": "12070", "verwijderd": false, "id": "12070", "laatst_aangepastdatum": "2013-11-24T04:59:35"}, "realisatie": {"titel": {"tekst": "Polygoon Hollands Nieuws", "bron": "Avail TITEL", "type": "Titel"}, "distributiekanaal": "bioscoop", "aanmaakdatum": "2013-11-24T04:59:35", "overige_titels": [{"tekst": "polhn#Polygoon Hollands Nieuws", "bron": "Prodic", "type": "ProdicTitel"}], "parent_id": "12068", "niveaus": [{"genres": ["journaal"], "taalID": "1", "intentieID": "1", "samenvatting": "Bioscoopjournaals waarin Nederlandse onderwerpen van een bepaalde week worden gepresenteerd.", "deelcatalogi": ["Bewegend beeld/Polygoon/Hollands nieuws"], "taakID": "28573"}, {"beschrijving": "Het Polygoon-journaal is decennialang h\u00e9t bioscoopjournaal in Nederland. In januari 1922 beginnen de eerste wekelijkse filmjournaals onder de titel 'Hollandsch nieuws'. Tot 1986 blijft het Polygoonjournaal bestaan. Daarna stopt het, omdat het bioscoopjournaal definitief is 'ingehaald' door de dagelijkse televisiejournaals. Philip Bloemendal (1918-1999) is veertig jaar lang d\u00e9 stem van Polygoon.", "genres": ["Nieuws"], "taalID": "1", "taakID": "29772", "intentieID": "2"}], "laatst_aangepastdatum": "2013-11-24T04:59:35", "id": "12070", "verwijderd": false}, "werk": {"titel": {"tekst": "Polygoon bioscoopjournaal", "type": "uniforme titel"}, "aanmaakdatum": "2013-11-24T05:02:23", "overige_titels": [{"tekst": "polhn#Polygoon bioscoopjournaal", "bron": "Prodic", "type": "ProdicTitel"}], "niveaus": [{"taalID": "1", "taakID": "28553", "intentieID": "1"}], "laatst_aangepastdatum": "2013-11-24T05:02:23", "id": "12068", "verwijderd": false}}